abenity/__init__.py
abenity/client.py
abenity-1.5.0.dist-info/LICENSE
abenity-1.5.0.dist-info/METADATA
abenity-1.5.0.dist-info/WHEEL
abenity-1.5.0.dist-info/top_level.txt
abenity-1.5.0.dist-info/RECORD
