Metadata-Version: 2.1
Name: abenity
Version: 1.5.0
Summary: Abenity API client
Home-page: https://github.com/abenity/abenity-python
Author: Abenity
License: MIT
Classifier: Development Status :: 3 - Alpha
Classifier: Intended Audience :: Developers
Classifier: Operating System :: OS Independent
Classifier: Topic :: Internet :: WWW/HTTP
Classifier: License :: OSI Approved :: MIT License
Classifier: Programming Language :: Python :: 2
Classifier: Programming Language :: Python :: 2.7
Classifier: Programming Language :: Python :: 3.10
License-File: LICENSE
Requires-Dist: requests >=2.32.3
Requires-Dist: pycryptodome ==3.20
Requires-Dist: six ==1.16.0
Provides-Extra: testing
Requires-Dist: pytest ; extra == 'testing'
